{"cameraMode":{"drawMode":0,"name":"Shaded","section":"Shading Mode"},"sceneLighting":true,"audioPlay":false,"sceneViewState":{"showFog":true,"showMaterialUpdate":false,"showSkybox":true,"showFlares":true,"showImageEffects":true,"showParticleSystems":true},"in2DMode":false,"pivot":{"x":-37.939605712890628,"y":-4.3775315284729,"z":-46.17050552368164},"rotation":{"x":-0.0206694845110178,"y":0.9027791023254395,"z":-0.04364510253071785,"w":-0.42743343114852908},"size":34.39649963378906,"orthographic":false}